<retConsReciNFe versao="3.10" xmlns="http://www.portalfiscal.inf.br/nfe"><tpAmb>2</tpAmb><verAplic>SP_NFE_PL_008i2</verAplic><nRec>351000100949320</nRec><cStat>104</cStat><xMotivo>Lote processado</xMotivo><cUF>35</cUF><dhRecbto>2016-07-08T12:16:05-03:00</dhRecbto><protNFe versao="3.10"><infProt><tpAmb>2</tpAmb><verAplic>SP_NFE_PL_008i2</verAplic><chNFe>35160754988308000116550010000097141000000792</chNFe><dhRecbto>2016-07-08T12:16:07-03:00</dhRecbto><cStat>252</cStat><xMotivo>Rejeição: Ambiente informado diverge do Ambiente de recebimento</xMotivo></infProt></protNFe></retConsReciNFe>
